{"files": [{"path": "android/0005-wangluoyingyong/0002-WIFI/0000-AndroidzhongdiWIFImokuai(yi).md", "rname": "0000-Android\u4e2d\u7684WIFI\u6a21\u5757(\u4e00).md", "mtime": 1424835166.0, "mode": "file", "name": "0000-AndroidzhongdiWIFImokuai(yi).md"}, {"path": "android/0005-wangluoyingyong/0002-WIFI/0001-AndroidzhongdiWIFImokuai(er).md", "rname": "0001-Android\u4e2d\u7684WIFI\u6a21\u5757(\u4e8c).md", "mtime": 1424835166.0, "mode": "file", "name": "0001-AndroidzhongdiWIFImokuai(er).md"}, {"path": "android/0005-wangluoyingyong/0002-WIFI/0002-AndroidzhongdiWIFImokuai(san).md", "rname": "0002-Android\u4e2d\u7684WIFI\u6a21\u5757(\u4e09).md", "mtime": 1424835166.0, "mode": "file", "name": "0002-AndroidzhongdiWIFImokuai(san).md"}, {"path": "android/0005-wangluoyingyong/0002-WIFI/0003-AndroidzhongdiWIFImokuai(si).md", "rname": "0003-Android\u4e2d\u7684WIFI\u6a21\u5757(\u56db).md", "mtime": 1424835166.0, "mode": "file", "name": "0003-AndroidzhongdiWIFImokuai(si).md"}, {"path": "android/0005-wangluoyingyong/0002-WIFI/0004-Android WIFIwangluocaozuo.md", "rname": "0004-Android WIFI\u7f51\u7edc\u64cd\u4f5c.md", "mtime": 1424835166.0, "mode": "file", "name": "0004-Android WIFIwangluocaozuo.md"}, {"path": "android/0005-wangluoyingyong/0002-WIFI/0005-AndroidzhongdiWifijieshaozuo.md", "rname": "0005-Android\u4e2d\u7684Wifi\u4ecb\u7ecd\u4f5c.md", "mtime": 1424835166.0, "mode": "file", "name": "0005-AndroidzhongdiWifijieshaozuo.md"}, {"path": "android/0005-wangluoyingyong/0002-WIFI/0006-Android WIFIjianceyushezhi.md", "rname": "0006-Android WIFI\u68c0\u6d4b\u4e0e\u8bbe\u7f6e.md", "mtime": 1424835166.0, "mode": "file", "name": "0006-Android WIFIjianceyushezhi.md"}, {"path": "android/0005-wangluoyingyong/0002-WIFI/0007-Android duiWifijinhangcaozuo.md", "rname": "0007-Android \u5bf9Wifi\u8fdb\u884c\u64cd\u4f5c.md", "mtime": 1424835166.0, "mode": "file", "name": "0007-Android duiWifijinhangcaozuo.md"}, {"path": "android/0005-wangluoyingyong/0002-WIFI/0008-Android SDK zhongAndroid.net.wifijianyaofenxi.md", "rname": "0008-Android SDK \u4e2dAndroid.net.wifi\u7b80\u8981\u5206\u6790.md", "mtime": 1424835166.0, "mode": "file", "name": "0008-Android SDK zhongAndroid.net.wifijianyaofenxi.md"}, {"path": "android/0005-wangluoyingyong/0002-WIFI/0009-Android WIFIdidakaiyuguanbiWifiManagerduixiangdishiyong.md", "rname": "0009-Android WIFI\u7684\u6253\u5f00\u4e0e\u5173\u95edWifiManager\u5bf9\u8c61\u7684\u4f7f\u7528.md", "mtime": 1424835166.0, "mode": "file", "name": "0009-Android WIFIdidakaiyuguanbiWifiManagerduixiangdishiyong.md"}, {"path": "android/0005-wangluoyingyong/0002-WIFI/0010-Android Wififangfadaquan.md", "rname": "0010-Android Wifi\u65b9\u6cd5\u5927\u5168.md", "mtime": 1424835166.0, "mode": "file", "name": "0010-Android Wififangfadaquan.md"}, {"path": "android/0005-wangluoyingyong/0002-WIFI/0011-Android dajiachangyongdiWIFI.md", "rname": "0011-Android \u5927\u5bb6\u5e38\u7528\u7684WIFI.md", "mtime": 1425793700.0, "mode": "file", "name": "0011-Android dajiachangyongdiWIFI.md"}, {"path": "android/0005-wangluoyingyong/0002-WIFI/0012-Android zidaidiwifiyizhi.md", "rname": "0012-Android \u81ea\u5e26\u7684wifi\u79fb\u690d.md", "mtime": 1424835166.0, "mode": "file", "name": "0012-Android zidaidiwifiyizhi.md"}, {"path": "android/0005-wangluoyingyong/0002-WIFI/0013-guanyuWIFIdikaiqiguanbiyulianjieredian.md", "rname": "0013-\u5173\u4e8eWIFI\u7684\u5f00\u542f\u5173\u95ed\u4e0e\u8fde\u63a5\u70ed\u70b9.md", "mtime": 1424835166.0, "mode": "file", "name": "0013-guanyuWIFIdikaiqiguanbiyulianjieredian.md"}, {"path": "android/0005-wangluoyingyong/0002-WIFI/0014-GPS,WIFI,GPRSkaiguanwenti.md", "rname": "0014-GPS,WIFI,GPRS\u5f00\u5173\u95ee\u9898.md", "mtime": 1424835166.0, "mode": "file", "name": "0014-GPS,WIFI,GPRSkaiguanwenti.md"}, {"path": "android/0005-wangluoyingyong/0002-WIFI/0015-AndroidpingtaizhongWifidichushihua.md", "rname": "0015-Android\u5e73\u53f0\u4e2dWifi\u7684\u521d\u59cb\u5316.md", "mtime": 1424835166.0, "mode": "file", "name": "0015-AndroidpingtaizhongWifidichushihua.md"}], "rname": "0002-WIFI", "name": "0002-WIFI", "mode": "tree", "mtime": 1424866980.0, "path": "android/0005-wangluoyingyong/0002-WIFI"}